favicon_hash/__init__.py
favicon_hash/cli.py
shodafinder-1.0.3.dist-info/LICENSE
shodafinder-1.0.3.dist-info/METADATA
shodafinder-1.0.3.dist-info/WHEEL
shodafinder-1.0.3.dist-info/entry_points.txt
shodafinder-1.0.3.dist-info/top_level.txt
shodafinder-1.0.3.dist-info/RECORD
