Metadata-Version: 2.1
Name: shodafinder
Version: 1.0.3
Summary: A simple Python script to compute the Shodan hash for a website's favicon
Home-page: https://github.com/logm1lo/Shodafinder
Author: Thanh Sang
Author-email: logm1lo <logmilo12@gmail.com>
Project-URL: Homepage, https://github.com/logm1lo/Shodafinder
Project-URL: Issues, https://github.com/logm1lo/Shodafinder/issues
Classifier: Programming Language :: Python :: 3
Classifier: License :: OSI Approved :: GNU General Public License v3 (GPLv3)
Classifier: Operating System :: OS Independent
Requires-Python: >=3.6
License-File: LICENSE
Requires-Dist: requests
Requires-Dist: mmh3
Requires-Dist: favicon
